{"ocr_results":[{"text":"他，他就出口骂人。","box":[[223,125],[485,123],[485,150],[223,152]]},{"text":"1962年2月25日：六队社员反映一队务委员遇到矛盾绕开走，","box":[[288,170],[1196,167],[1196,194],[288,197]]},{"text":"民","box":[[19,192],[106,186],[113,286],[25,292]]},{"text":"当“小乖人”，拿集体的“肥田粉”撒在自留地里。","box":[[226,217],[892,216],[892,243],[226,244]]},{"text":"1962年5月13日：冯书记报告说：“当前有一股邪气，无根据造","box":[[288,263],[1193,259],[1193,288],[288,292]]},{"text":"谣，伤害集体的柏树，掏树根，随便拿大队的物资·\"","box":[[219,309],[991,298],[992,336],[219,347]]},{"text":"1963年2月25日：通知“新四种人”27日到大队报到，时间三","box":[[288,356],[1189,352],[1189,380],[288,384]]},{"text":"天：1.骂人打人的；2.翻坟的；3.赌博的；4.翻公家树根的。","box":[[222,404],[1097,401],[1097,428],[222,431]]},{"text":"1963年12月5日：5队地区偷掉二根落田管，据反映是6队的","box":[[287,450],[1192,448],[1192,475],[287,477]]},{"text":"两个人偷的。","box":[[226,499],[403,499],[403,523],[226,523]]},{"text":"《笔记》中所记录的只是极少数事例，许许多多此类事件都随着时间","box":[[220,589],[1192,587],[1192,614],[220,616]]},{"text":"之水流逝了，尽管有些曾在当时引起过或大或小的波澜。在生产队里，如","box":[[154,635],[1193,633],[1193,659],[154,661]]},{"text":"制","box":[[49,685],[139,685],[139,726],[49,726]]},{"text":"果侵害集体利益的行为被人发现，人际关系就会出现张力。人们通常对","box":[[153,680],[1195,679],[1195,706],[153,707]]},{"text":"此采取四种不同的处理方式。或者当场揭发。如在收获番薯的时候，有","box":[[155,730],[1192,728],[1192,752],[155,754]]},{"text":"人故意将好番薯留在地里，以便让自已的小孩来“掠”，在场劳动的农民会","box":[[156,776],[1193,776],[1193,800],[156,800]]},{"text":"度","box":[[47,813],[150,813],[150,853],[47,853]]},{"text":"出现指责这种损害大家利益的行为。或者视而不见。如有人发现自己的","box":[[155,823],[1193,823],[1193,847],[155,847]]},{"text":"亲戚朋友千这类事情，他们的行为又不直接影响自己的利益，那么，碍于","box":[[156,870],[1193,870],[1193,894],[156,894]]},{"text":"情面关系，他可能取漠然置之的态度。或者背着当事人议论、反映。《笔","box":[[154,914],[1194,913],[1194,940],[154,941]]},{"text":"研","box":[[47,936],[128,936],[128,978],[47,978]]},{"text":"记》中的事例都是有人向上反映的记录。或者着意模仿。人们想“他拿，","box":[[153,959],[1193,960],[1193,987],[153,986]]},{"text":"我也好拿”“他这样做，我也可以做”，假如这种想法蔓延开来，个别的损","box":[[154,1007],[1191,1007],[1191,1034],[154,1034]]},{"text":"究","box":[[47,1059],[131,1059],[131,1100],[47,1100]]},{"text":"害集体利益的行为就会演变成普遍的行为。生产队里曾经发生过这种情","box":[[154,1053],[1193,1053],[1193,1080],[154,1080]]},{"text":"况。有一次，有人挖地里的树根，其他人一个个跟着仿效，后来，连队里最","box":[[153,1099],[1192,1100],[1192,1127],[153,1126]]},{"text":"老实的人也耐不住了。“挖树根是不好，但大家都在挖，我不去，不是吃亏","box":[[155,1146],[1192,1147],[1192,1174],[155,1173]]},{"text":"了么？”如此想着，他也加入了挖树根的行列。事情越闹越大，甚至队里的","box":[[155,1194],[1191,1195],[1191,1219],[155,1218]]},{"text":"活桑树也被人连根拔起，直到大队出面干预，风波才算平息下来。","box":[[154,1239],[1070,1241],[1070,1267],[154,1265]]},{"text":"公社因.上地和财产的集体所有制度而引出了侵害集体利益问题，因","box":[[220,1286],[1192,1287],[1192,1314],[220,1313]]},{"text":"共同劳动而引出了劳动计酬问题，因产品分配而引出了按劳按需比例的","box":[[153,1332],[1192,1335],[1192,1362],[153,1359]]},{"text":"同题。自从实行“三级所有，队为基础”的新体制以后，尽管公社设计了种","box":[[152,1380],[1192,1382],[1192,1409],[152,1407]]},{"text":"种解决问题的方案，其中包括超经济强制和阶级斗争，但是，不同的解决","box":[[152,1425],[1193,1428],[1193,1456],[152,1452]]},{"text":"方案只不过改变了问题的展现方式，而没有解决问题本身。问题是“胎生","box":[[152,1471],[1193,1473],[1193,1500],[152,1498]]},{"text":"的”，公社无法消除胎里带来的印记。","box":[[153,1518],[666,1519],[666,1546],[153,1545]]},{"text":"生产队类似于传统的大家庭，土地共有，共同劳动；生产队又不同·于","box":[[219,1564],[1192,1567],[1192,1594],[219,1591]]},{"text":"传统的大家庭·队里的每一个农户都是独立的消费单位。这种不同追使","box":[[152,1609],[1192,1613],[1192,1643],[152,1639]]},{"text":"生产队建立完整的簿记制度，首先是劳动计酬，其次才是产品分配。农业","box":[[151,1657],[1191,1662],[1191,1689],[151,1684]]},{"text":"劳动是非标准性的，种类繁多，质量难以检验，劳动计酬因此十分复杂，几","box":[[151,1704],[1191,1708],[1191,1735],[151,1731]]},{"text":"乎不可能公平合理。从农业合作化运动以来，农村已经发展出一整套劳","box":[[154,1750],[1190,1755],[1190,1782],[154,1777]]},{"text":"动计酬的制度，主要包括评定底分、按时记分、定额记分等等。这套制度","box":[[151,1797],[1190,1801],[1190,1828],[151,1824]]},{"text":"每天运作，但每天都在纷繁的纠纷和无休止的争执中运作，常常令运作者","box":[[151,1843],[1189,1848],[1189,1876],[151,1870]]},{"text":"-104-","box":[[623,1913],[720,1913],[720,1942],[623,1942]]}],"dimensions":{"height":2075,"width":1350}}