{"ocr_results":[{"text":"'","box":[[80,111],[103,116],[101,124],[78,119]]},{"text":"大队，反映生产队里有人提出张海红的家庭出身问题。","box":[[226,122],[994,121],[994,148],[226,149]]},{"text":"但是，公社不可能把村落完全封闭起来，社会也会产生从村落中吸纳","box":[[225,215],[1197,214],[1197,241],[225,242]]},{"text":"人员的需求。对于村落里的年轻农民来说，一旦出现可能脱离农业劳动","box":[[154,262],[1197,261],[1197,288],[154,289]]},{"text":"的机会，他们都会积极地去争取。浙北农村有一句人人皆知的俗语：“好","box":[[157,309],[1196,308],[1196,335],[157,336]]},{"text":"铁不打钉，好男不当兵”，村里的老年人都能绘声绘色地讲出过去的农民","box":[[159,356],[1193,356],[1193,380],[159,380]]},{"text":"巧妙地躲避当兵的故事。然而，现在生产队里的年轻人却都踊跃报名参","box":[[155,400],[1198,401],[1198,431],[155,430]]},{"text":"军，与参军可能带来的风险和经济损失相比，参军为年轻人提供的走出村","box":[[159,451],[1194,451],[1194,475],[159,475]]},{"text":"落、脱离农业劳动的机会更具有诱惑性。那时候，甚至不少农村姑娘也把","box":[[156,495],[1196,497],[1196,524],[156,522]]},{"text":"1","box":[[52,513],[116,513],[116,551],[52,551]]},{"text":"：","box":[[32,534],[79,529],[81,547],[34,552]]},{"text":"选择对象的目光投向现役军人，有的人梦想着作为随军家属离开农村。","box":[[156,542],[1195,543],[1195,570],[156,569]]},{"text":"1973年，浙北农村开展“贫下中农推荐上大学”的工作，那些只有初中甚","box":[[155,588],[1195,590],[1195,617],[155,615]]},{"text":"至小学文化程度的农民根本不明白上大学是怎么回事，但又胧地觉得","box":[[158,635],[1193,637],[1193,663],[158,661]]},{"text":"制","box":[[51,684],[150,684],[150,725],[51,725]]},{"text":"这是一次机会，于是纷纷报名，L大队报名要求上大学的竞有四五十人之","box":[[151,682],[1194,684],[1194,711],[151,709]]},{"text":"多。多年以后回忆此事，有人笑自己当年是“癫蛤想吃天鹅肉，不自量","box":[[156,729],[1194,731],[1194,757],[156,755]]},{"text":"力”。但这件事情本身可以证明，生产队里的年轻人中存在着普遍的“走","box":[[156,775],[1194,778],[1194,805],[156,802]]},{"text":"度","box":[[50,810],[159,810],[159,850],[50,850]]},{"text":"出去”的冲动。","box":[[154,823],[353,823],[353,850],[154,850]]},{"text":"在公社时期，农民完全脱离村落的机会很少，一旦这种机会来临，村","box":[[221,869],[1194,872],[1194,899],[221,896]]},{"text":"里就会出现一些震荡。在事情过去以后，在有缘离开村落的农民欢快地","box":[[155,916],[1193,918],[1193,945],[155,943]]},{"text":"研 ","box":[[51,935],[99,935],[99,972],[51,972]]},{"text":"、","box":[[1276,952],[1301,952],[1301,968],[1276,968]]},{"text":"打点行装出发以后，这些人对于生产队的影响几近消失。但是，那些脱离","box":[[154,962],[1193,965],[1193,993],[154,990]]},{"text":"农业劳动而又继续留在生产队黑的人却直接影响着农业的集体经营。","box":[[154,1010],[1144,1012],[1144,1039],[154,1036]]},{"text":">","box":[[1274,1008],[1289,1008],[1289,1033],[1274,1033]]},{"text":"究","box":[[49,1060],[88,1060],[88,1097],[49,1097]]},{"text":"其一，外出的农民通常拿现金工资，收人比队里高，干的活未必比农","box":[[220,1056],[1194,1059],[1194,1086],[220,1083]]},{"text":"活辛苦。与外出人员相比，留在队里的农民相形见出。“水往低处流，人","box":[[155,1103],[1193,1106],[1193,1133],[155,1130]]},{"text":"向高处走”，农民因受到外出的诱惑而不安心农业，外出的人越多，生产队","box":[[155,1150],[1191,1153],[1191,1180],[155,1177]]},{"text":"农业经营的组织就越困难。","box":[[153,1197],[536,1198],[536,1225],[153,1224]]},{"text":"其二，外出的农民不参加生产队里的劳动，但继续拿生产队里的粮","box":[[218,1244],[1192,1247],[1192,1273],[218,1270]]},{"text":"食。他们中的许多人不交公积金和公益金，拿粮食也不付钱，任欠账“倒","box":[[154,1291],[1193,1294],[1193,1321],[154,1318]]},{"text":"挂”1在会计的账本上。这就引起了务农者的不满，引起了务农者与外出","box":[[153,1337],[1191,1342],[1191,1369],[153,1364]]},{"text":"者之间的矛盾。一名青年农民当时说，我们耕地种用打粮食，他们白拿粮","box":[[154,1386],[1192,1389],[1192,1415],[154,1412]]},{"text":"食不付钱，这是剥削我们的劳动。一名民办教师回忆说：“那时下午四点","box":[[153,1432],[1191,1435],[1191,1462],[153,1458]]},{"text":"半左右学校放学，夏天日子长，学校放学了，农民刚刚吃完点心上工。回","box":[[153,1478],[1192,1481],[1192,1508],[153,1505]]},{"text":"家的时候，我常绕开农民干活的地方，否则，地里的农民会指着你说上一","box":[[152,1524],[1189,1529],[1189,1556],[152,1551]]},{"text":"大堆冷嘲热讽的难听话，让你心里觉得十分难受。”","box":[[153,1573],[871,1573],[871,1600],[153,1600]]},{"text":"其三，农民的外出有两种情况，一是“组织安排”的外出，如进乡村集","box":[[217,1618],[1189,1623],[1189,1650],[217,1645]]},{"text":"体企业等等：一是农民自已找门路外出，如做泥水匠、木匠等等。以第一","box":[[153,1665],[1190,1669],[1190,1697],[153,1693]]},{"text":"种方式外出的农民或多或少仍受到组织的制约，例如，在生产队农忙的时","box":[[151,1713],[1190,1717],[1190,1744],[151,1740]]},{"text":"①在生产队会计的年终决算经济分配到户表中，最后两栏是“队找户金额”和“户找队金","box":[[199,1814],[1189,1819],[1189,1843],[199,1838]]},{"text":"额”，前者指生产队给农户现金·后者指农户向生产队交现金。后者俗称“倒挂”。","box":[[151,1848],[1015,1852],[1014,1876],[151,1871]]},{"text":"-230-","box":[[620,1913],[720,1913],[720,1941],[620,1941]]}],"dimensions":{"height":2075,"width":1350}}