{"ocr_results":[{"text":"件的地方，生产队可以按照本队土地的情况，经过社员讨论，拨给社员适","box":[[160,111],[1197,115],[1197,142],[160,138]]},{"text":"当数量的饲料地。这种饲料地，应该尽可能利用现有的闲散地或者小片","box":[[160,158],[1195,161],[1195,188],[160,185]]},{"text":"荒地。","box":[[157,204],[239,204],[239,232],[157,232]]},{"text":"（三）经过生产队社员大会讨论和公社或者生产大队批准，在统","box":[[223,248],[1195,250],[1195,281],[223,279]]},{"text":"一规划下，可以开垦零星荒地。开垦的荒地一般可以相当于自留地","box":[[157,297],[1193,300],[1193,327],[157,324]]},{"text":"的数量，在人少地多的地方可以少一点，在人多地少的地方也可以略","box":[[154,343],[1192,346],[1192,372],[154,369]]},{"text":"多一点。","box":[[153,388],[277,391],[277,419],[152,416]]},{"text":"开荒绝对不许破坏水土保持，破坏山林，破坏草原，破坏水利工程，奶","box":[[222,436],[1193,441],[1193,467],[222,462]]},{"text":"碍交通。","box":[[151,481],[271,483],[271,511],[150,509]]},{"text":"社员的自留地、饲料地和开荒地合在一起的数量，根据各个地方土地","box":[[220,529],[1192,535],[1192,562],[220,556]]},{"text":"的不同情况，有多有少，在一般情况下，可以占生产队耕地面积的百分之","box":[[155,575],[1192,581],[1192,609],[155,603]]},{"text":"五到百分之十，最多不能超过百分之十五。","box":[[154,621],[753,626],[753,651],[154,647]]},{"text":"制","box":[[48,672],[85,672],[85,712],[48,712]]},{"text":"（四）进行编织、缝纫、刺绣等家庭手工业生产：","box":[[220,667],[876,671],[876,698],[220,694]]},{"text":"（五）从事采集、渔猎、养蚕、养蜂等副业生产。","box":[[219,715],[862,716],[862,744],[219,743]]},{"text":"（六）经营由集体分配的自留果树和竹木。在屋前屋后或者在生产","box":[[218,760],[1192,764],[1192,794],[218,790]]},{"text":"度","box":[[43,797],[164,797],[164,840],[43,840]]},{"text":"队指定的其他地方种植果树、桑树和竹木。这些东西永远归社员所有。","box":[[145,807],[1157,813],[1157,840],[145,834]]},{"text":"社员经营家庭副业，使用集体所有的牲畜和工具等生产资料的时候，","box":[[218,854],[1191,860],[1191,887],[218,881]]},{"text":"都要付给集体以适当的代价。","box":[[153,900],[569,903],[568,930],[153,927]]},{"text":"研","box":[[45,922],[86,922],[86,964],[45,964]]},{"text":"四十一、社员家庭副业的产品和收人，都归社员所有，都归社员支","box":[[218,947],[1189,954],[1189,981],[218,974]]},{"text":"配。在完成同国家订立的定购合同以后，除了国家有特殊限制的以外，其","box":[[150,994],[1189,1000],[1189,1027],[150,1020]]},{"text":"究","box":[[38,1046],[155,1033],[160,1076],[43,1089]]},{"text":"余的产品，都可以拿到集市上出售。","box":[[145,1039],[651,1043],[651,1069],[145,1066]]},{"text":"社员的自留地和开荒地生产的农产品，不算在集体分配的产量和集","box":[[215,1086],[1187,1093],[1187,1120],[215,1113]]},{"text":"体分配的口粮以内，国家不征收农业税，不计统购。","box":[[149,1133],[866,1138],[866,1164],[149,1159]]},{"text":"四十二、人民公社各级管理委员会，对于社员经营家庭副业，应该给","box":[[217,1179],[1185,1187],[1185,1214],[217,1206]]},{"text":"以必要的指导和帮助，不要乱加于涉。同时，又要教育社员兼顾国家、集","box":[[149,1225],[1185,1234],[1185,1261],[149,1252]]},{"text":"体和个人的利益，积极参加和关心集体生产，不损害公共利益，不弃农经","box":[[147,1271],[1185,1280],[1185,1307],[147,1298]]},{"text":"商，不投机倒把。","box":[[147,1317],[376,1320],[375,1348],[147,1345]]},{"text":"对于生活困难的社员，生产队应该在家庭副业方面，例如养猪、编织","box":[[212,1365],[1184,1373],[1184,1401],[212,1393]]},{"text":"等，注意帮他们解决困难，增加收人。","box":[[146,1411],[659,1416],[659,1444],[146,1438]]},{"text":"四十三、人民公社各级组织、供销合作社、手工业合作社和国家指定","box":[[215,1460],[1183,1468],[1183,1494],[215,1487]]},{"text":"的国营企业，可以根据社员自和公私两利的原则，分别采取加工、定货、","box":[[146,1504],[1184,1514],[1184,1541],[146,1531]]},{"text":"代购原料、代销产品、收购产品和公有私养等适当的方式，帮助社员家庭","box":[[144,1551],[1183,1560],[1183,1588],[144,1579]]},{"text":"副业和集体经济或者国营经济联系起来。","box":[[144,1597],[726,1604],[726,1631],[144,1624]]},{"text":"第六章社","box":[[487,1692],[709,1692],[709,1727],[487,1727]]},{"text":"员","box":[[699,1691],[840,1691],[840,1733],[699,1733]]},{"text":"四十四、人民公社社员，在社内享有政治、经济、文化、生活福利等方","box":[[209,1786],[1178,1797],[1178,1824],[209,1813]]},{"text":"面一切应该享受的权利。人民公社的各级组织，对于社员的一切权利，都","box":[[142,1830],[1180,1842],[1180,1869],[142,1857]]},{"text":"- 422-","box":[[611,1900],[710,1905],[708,1936],[609,1931]]}],"dimensions":{"height":2075,"width":1350}}