{"ocr_results":[{"text":"1650","box":[[94,88],[150,88],[150,114],[94,114]]},{"text":"周恩来传","box":[[339,86],[465,86],[465,113],[339,113]]},{"text":"周恩来的这个报告，反映出中国共产党人在实","box":[[135,150],[722,150],[722,174],[135,174]]},{"text":"践中探索，对经济工作的客观规律的认识正在走向","box":[[76,188],[722,190],[721,214],[76,212]]},{"text":"深化。","box":[[73,227],[147,227],[147,255],[73,255]]},{"text":"八大在九月二十七日通过了《关于发展国民经","box":[[136,268],[722,268],[722,292],[136,292]]},{"text":"济的第二个五年计划（一九五八一一一九六二年）的","box":[[76,308],[722,308],[722,332],[76,332]]},{"text":"建议》。在同一天通过的《关于政治报告的决议》中","box":[[76,347],[722,347],[722,371],[76,371]]},{"text":"写道：","box":[[73,384],[149,384],[149,413],[73,413]]},{"text":"我们“有可能高速度地发展我们的生产力。","box":[[192,427],[721,427],[721,450],[192,450]]},{"text":"如果对于这种可能性估计不足，或者不努力把","box":[[135,469],[721,469],[721,492],[135,492]]},{"text":"这种可能性变为现实性，那就是保守主义的错","box":[[135,512],[722,512],[722,535],[135,535]]},{"text":"误。但是，我们也必须估计到当前的经济上、财","box":[[135,554],[722,554],[722,577],[135,577]]},{"text":"政上和技术力量上的客观限制，估计到保持后","box":[[135,596],[721,596],[721,619],[135,619]]},{"text":"备力量的必要，而不应当脱离经济发展的正确","box":[[136,638],[721,638],[721,661],[136,661]]},{"text":"比例。如果不估计到这些情况而规定一种过高","box":[[135,681],[722,681],[722,705],[135,705]]},{"text":"的速度，结果就会反而妨碍经济的发展和计划","box":[[134,723],[722,723],[722,747],[134,747]]},{"text":"的完成，那就是冒险主义的错误。党的任务，就","box":[[135,766],[721,766],[721,789],[135,789]]},{"text":"是要随时注意防止和纠正右倾保守的或‘左’倾","box":[[134,806],[723,809],[722,832],[134,830]]},{"text":"冒险的倾向，积极地而又稳妥可靠地推进国民","box":[[136,851],[722,851],[722,874],[136,874]]},{"text":"经济的发展。\"①","box":[[132,892],[326,889],[327,916],[132,919]]},{"text":"在八大的正确决策下，国民经济在一段时间内","box":[[134,935],[721,935],[721,958],[134,958]]},{"text":"《建国以来重要文献选编》第9册，中央文献出版社1994年","box":[[159,1019],[724,1019],[724,1042],[159,1042]]},{"text":"8月版，第347页。","box":[[159,1055],[336,1055],[336,1076],[159,1076]]}],"dimensions":{"height":1140,"width":794}}