{"ocr_results":[{"text":"好，不是小好。整个形势比以往任何时候都好。”形势大好的重要标志是“人民群众充分","box":[[152,158],[1121,158],[1121,180],[152,180]]},{"text":"发动起来了”，“大家都在关心国家大事”，连一家人在一起也要辩论文化大革命的事","box":[[154,197],[1096,197],[1096,217],[154,217]]},{"text":"情。“有些地方前一段好像很乱，其实那是乱了敌人，锻炼了群众。”","box":[[150,233],[915,232],[915,256],[150,257]]},{"text":"毛泽东一路大讲大联合。他说：“在工人阶级内部，没有根本利害冲突。在无产阶级","box":[[202,271],[1122,272],[1122,293],[202,292]]},{"text":"专政下的工人阶级内部，更没有理由一定要分成势不两立的两大派组织。一个工厂，分成","box":[[154,310],[1122,310],[1122,330],[154,330]]},{"text":"两派，主要是走资本主义道路的当权派为了保自己，蒙蔽群众，挑动群众斗群众。群众组","box":[[153,346],[1121,347],[1121,368],[153,367]]},{"text":"织里头，混进了坏人，这是极少数。有些群众组织受无政府主义的影响，也是一个原","box":[[151,384],[1071,385],[1071,406],[151,405]]},{"text":"因。”","box":[[150,421],[219,418],[219,443],[151,445]]},{"text":"“只要两派都是革命的群众组织，就要在革命的原则下实现革命的大联合。两派要互","box":[[210,457],[1122,458],[1122,482],[210,481]]},{"text":"相少讲别人的缺点、错误，别人的缺点、错误让人家自己讲，各自多作自我批评，求大","box":[[153,497],[1096,497],[1096,517],[153,517]]},{"text":"同，存小异。”","box":[[154,535],[313,535],[313,556],[154,556]]},{"text":"他还批评了大联合中的“以我为核心”的问题。他说：“什么“以我为核心”，这个","box":[[204,572],[1122,572],[1122,592],[204,592]]},{"text":"问题要解决。核心是在斗争中实践中群众公认的，不是自封的。土明、博古、张闻大，他","box":[[155,612],[1121,612],[1121,629],[155,629]]},{"text":"要做核心，要人家承认他是核心，结果垮台了。”","box":[[151,646],[692,645],[692,667],[151,668]]},{"text":"毛泽东在谈话中，多次讲到对待干部问题。他说：“绝大多数的干部都是好的，不好","box":[[201,683],[1122,684],[1122,707],[201,706]]},{"text":"的只是极少数。”“要团结干部的大多数”。“有些干部为什么受到群众批判斗争呢？一","box":[[152,721],[1110,721],[1110,744],[152,744]]},{"text":"个是资产阶级反动路线，群众有气。一个是官做大了，薪水多了，自以为了不起，就摆架","box":[[152,758],[1123,759],[1123,781],[152,780]]},{"text":"子，有事不同群众商量，不平等待人，不民主，喜欢骂人、训人，严重脱离群众。这样，","box":[[155,797],[1111,797],[1111,817],[155,817]]},{"text":"群众就有意见。平时没有机会讲，无产阶级文化大革命中爆发了，一爆发，就不得了，弄","box":[[152,834],[1122,835],[1122,856],[152,855]]},{"text":"得他们很狼狈。”","box":[[151,872],[342,869],[343,892],[152,896]]},{"text":"最后，毛泽东说：“要告诉革命造反派的头头和红卫兵小将们，现在是他们有可能犯","box":[[203,910],[1121,910],[1121,930],[203,930]]},{"text":"错误的时候。要用我们自己犯错误的经验教训，教育他们。”","box":[[152,946],[816,947],[816,968],[152,967]]},{"text":"毛泽东号召全国人民：“要斗私，批修”，“要拥军爱民，要抓革命，促生产，促战","box":[[203,984],[1123,984],[1123,1006],[203,1006]]},{"text":"备”。","box":[[151,1018],[216,1022],[214,1047],[150,1043]]},{"text":"周恩来解决黑龙江省两派问题，自始至终，忠实地贯彻上述精神。","box":[[203,1061],[912,1061],[912,1081],[203,1081]]},{"text":"周恩来解决黑龙江省的问题，首先亲自搞了大量的调查。他夜以继日，不辞辛劳地一","box":[[203,1098],[1124,1098],[1124,1118],[203,1118]]},{"text":"派一派地听取汇报，口问手记，慈父般地反反复复地做工作。前前后后，周恩来分别同","box":[[153,1135],[1096,1135],[1096,1155],[153,1155]]},{"text":"潘、汪以及两派分别谈话各八、九次，两派在一起三次。","box":[[151,1171],[763,1172],[763,1193],[151,1192]]},{"text":"周恩来首先抓制止武斗。当时黑龙江省，主要是哈尔滨，由于潘复生坚持对炮轰派的","box":[[202,1210],[1122,1209],[1122,1230],[202,1231]]},{"text":"高压政策，凡是出现炮轰派的单位，或是对于出现与他不同意见的组织，一律看成炮轰","box":[[153,1247],[1097,1247],[1097,1267],[153,1267]]},{"text":"派，他总是依照6·9夺权的固定模式，调动捍联总的人马先围攻后夺权。致使哈尔滨的武","box":[[153,1286],[1108,1286],[1108,1306],[153,1306]]},{"text":"斗升级。","box":[[153,1323],[237,1323],[237,1344],[153,1344]]},{"text":"7月中旬，捍联总对哈一机炮轰派实行大包围，7月18日早晨、7月22日晚间，哈一机","box":[[198,1359],[1110,1360],[1110,1383],[198,1382]]},{"text":"炮轰派被迫发动了两次抢粮事件。","box":[[152,1397],[512,1398],[512,1419],[152,1418]]},{"text":"8月27日、28日，捍联总在哈一机厂和哈尔滨港务局等单位挑起武斗，双方动用了装","box":[[201,1437],[1110,1437],[1110,1457],[201,1457]]}],"dimensions":{"height":1650,"width":1275}}