{"ocr_results":[{"text":"部的敦促是远不及您们的身教的。","box":[[153,159],[512,160],[512,180],[153,179]]},{"text":"千言万语，根本希望就提一条，首长们，到群众中来吧！","box":[[201,194],[810,195],[810,218],[201,217]]},{"text":"群众需要您们来当学生，群众也需要您们来当先生。范正美同志有句话讲得好：“去","box":[[201,233],[1123,234],[1123,257],[201,256]]},{"text":"掉怕字，换成敢字，去掉私字，换成公字，虚心听取群众的批评和意见”，我们浴血奋战","box":[[153,273],[1122,273],[1122,293],[153,293]]},{"text":"得来的新政权就需要那些“既当官，又当老百姓”的同志，就需要那些“全心全意为人民","box":[[153,310],[1122,310],[1122,330],[153,330]]},{"text":"服务，一刻也不脱离群众”的好同志。","box":[[153,346],[567,346],[567,369],[153,369]]},{"text":"回顾四个多月来，中央对黑龙江英明、具体地解决，总理等中央首长们花费了多大的","box":[[205,386],[1122,386],[1122,406],[205,406]]},{"text":"精力啊！我们最红最红的红太阳，我们的红司令这样关心黑龙江省的文化大革命，我们还","box":[[153,422],[1109,422],[1109,442],[153,442]]},{"text":"有什么理由不尽快实现毛主席的伟大战略部署。熟阅中央文件，深思首长的讲话，那字里","box":[[152,460],[1122,460],[1122,480],[152,480]]},{"text":"行间，对今后的方向指得何等明确，多么语重心长啊！我们红色造反者绝不辜负党中央毛","box":[[153,497],[1110,497],[1110,517],[153,517]]},{"text":"主席的期望，为在黑龙江尽快实现毛主席的伟大战略部署，纵有刀山，我们敢上，有火","box":[[153,535],[1097,535],[1097,555],[153,555]]},{"text":"海，我们敢闯！“我们的战斗口号应当是不断革命！”我们誓作“决心把无产阶级文化大革","box":[[152,571],[1121,571],[1121,591],[152,591]]},{"text":"命进行到底的无产阶级革命派！”","box":[[153,610],[501,610],[501,630],[153,630]]},{"text":"敬爱的首长们，我们有战无不胜的毛泽东思想，相信党、相信群众，我们就一定能胜","box":[[203,648],[1122,648],[1122,667],[203,667]]},{"text":"利！","box":[[152,681],[191,684],[189,707],[150,705]]},{"text":"此致","box":[[200,721],[249,721],[249,743],[200,743]]},{"text":"无产阶级文化大革命的战斗敬礼","box":[[204,761],[546,761],[546,780],[204,780]]},{"text":"哈尔滨军工红色造反团","box":[[203,797],[447,797],[447,817],[203,817]]},{"text":"《小学生》战斗队普通一兵","box":[[214,835],[497,835],[497,855],[214,855]]},{"text":"1968年1月10日","box":[[203,872],[359,872],[359,892],[203,892]]},{"text":"这封信表达了当时一个普通大学生，对于中国共产党及其领袖、省一级党的领导干","box":[[201,908],[1096,909],[1096,930],[201,929]]},{"text":"部、对于当时形势及其促进革命联合、促进文革向理想方向发展的，质朴的思想情感、善","box":[[154,947],[1123,947],[1123,967],[154,967]]},{"text":"良的心境、良好的愿望和火热的心肠，至今读起来仍然有一股感人肺腑、催人泪下的力","box":[[153,984],[1095,985],[1095,1005],[153,1004]]},{"text":"量，虽然洋洋数千言，但情随境迁、语应理出，一点儿也不觉得冗长，人们从心里可以窥","box":[[154,1021],[1122,1021],[1122,1041],[154,1041]]},{"text":"见写信人的心扉，听到他在用心与潘复生对话。诚然，也可以通过这封信领略这位学生的","box":[[154,1060],[1123,1060],[1123,1080],[154,1080]]},{"text":"机智和过人的胆识之处，字里行间多少带有谈谐、幽默甚至讥讽，然而，潘复生所见的，","box":[[153,1098],[1111,1098],[1111,1118],[153,1118]]},{"text":"也许只有年轻人对他的崇敬和恭维，而尚未真正理解其真实含义，以及个中对他的揭露和","box":[[154,1135],[1122,1135],[1122,1155],[154,1155]]},{"text":"批评，所以将这封信原封未动地批给了常委们一阅，使我有可能转述在此。这位年轻人的","box":[[153,1171],[1122,1171],[1122,1191],[153,1191]]},{"text":"心境、情怀、热望，可以说是那个时代的一般大学生的写真。我们当时就是怀着这位年轻","box":[[151,1208],[1124,1209],[1124,1232],[151,1231]]},{"text":"人一样的真善美，而未知潘复生的假恶丑。所谓书生气，也许就是青年知识分子凭着自己","box":[[153,1247],[1122,1247],[1122,1267],[153,1267]]},{"text":"的良知和虔诚，去劝人放下屠刀，改恶从善，立地成佛，把复杂的政治人物理想化，过于","box":[[153,1285],[1122,1285],[1122,1305],[153,1305]]},{"text":"从好处想入非非了吧。我觉得这封信是一个很好的历史见证，因而我把它保留至今。","box":[[153,1323],[1060,1323],[1060,1343],[153,1343]]},{"text":"客观地说，刚回哈的一段日子，潘复生并没有马上搞什么动作，他甚至还交待我和刘","box":[[204,1360],[1122,1360],[1122,1380],[204,1380]]},{"text":"雪峰领导搞赵去非的调查。因为当时周恩来派的监督员一一总后的史一民副部长还在哈尔","box":[[154,1396],[1121,1396],[1121,1416],[154,1416]]},{"text":"滨。这位40出头的军人，中等身材，可是一位言语不多、真抓实十、极端负责的好十部，","box":[[153,1436],[1110,1436],[1110,1456],[153,1456]]},{"text":"成天坐车四处巡查。见潘复生发表红卫兵给他的信件，市面上又是那么平静，双方尚无大","box":[[154,1473],[1122,1473],[1122,1492],[154,1492]]}],"dimensions":{"height":1650,"width":1275}}