{"ocr_results":[{"text":"动影响生产、流通的问题。这在夺权前已如前述。","box":[[154,160],[687,160],[687,179],[154,179]]},{"text":"我在前面说过，在黑龙江省，经济主义于城市并没有泛滥成灾，而是蔓延到了农村。","box":[[204,197],[1111,197],[1111,217],[204,217]]},{"text":"为此，省革委会一成立便抓紧这方面的工作。于2月3日，由我签发了对全省农村的一份文","box":[[152,233],[1124,234],[1124,257],[152,256]]},{"text":"告，以省革委会的名义，向全省农业战线红色造反者发出一封公开信，大标题是“抓革命","box":[[154,272],[1123,272],[1123,292],[154,292]]},{"text":"促生产”，副标题是“彻底粉碎经济主义，打退资产阶级反动路线的新反扑”。文告分两","box":[[153,310],[1122,310],[1122,330],[153,330]]},{"text":"部分：第一部分列举了农村经济主义的七大表现：分掉生产费，少分或分掉公共积累，少","box":[[154,346],[1121,346],[1121,366],[154,366]]},{"text":"还贷款和机耕费，分掉储备粮，卖掉牛马、种子、农具等生产资料参加分配，乱发高工","box":[[152,384],[1097,385],[1097,406],[152,405]]},{"text":"分、高补贴用以鼓励农民进城，还有弄虚作假、制造土地纠纷、索取退赔款、瓜分社办企","box":[[153,422],[1122,422],[1122,442],[153,442]]},{"text":"业或国营企业、闹福利待遇等等。根据上述事实，我们向全省农村革命造反组织、造反","box":[[152,458],[1099,459],[1099,482],[152,481]]},{"text":"派，贫下中农、革命职工、革命干部发出了七项号召。号召大家，一定要学好毛泽东","box":[[153,497],[1072,497],[1072,517],[153,517]]},{"text":"的“老三篇”和《关于纠正党内的错误思想》等著作、《红旗》杂志、《人民日报》社论","box":[[153,535],[1122,535],[1122,555],[153,555]]},{"text":"以及省革委会的《一号通告》和拜泉县四个群众组织的《紧急呼吁》等文件。要充分发动","box":[[154,572],[1122,572],[1122,592],[154,592]]},{"text":"群众，运用各种形式，揭发阴谋策划者，将他们斗垮斗臭。要把生产队的粮食、现金、库","box":[[153,609],[1121,609],[1121,629],[153,629]]},{"text":"存物资等，查封起来，不经革命群众批准不准动用。第二部分不太长，主要是号召抓紧备","box":[[153,648],[1122,648],[1122,667],[153,667]]},{"text":"耕生产，莫失时机，做到春耕生产和文化大革命两不误。","box":[[153,685],[764,685],[764,705],[153,705]]},{"text":"根据春耕在即、不违农时的想法，于2月13日，我签发了省革委会《关于掀起备耕生","box":[[203,722],[1109,722],[1109,742],[203,742]]},{"text":"产高潮的动员令》。《动员令》说，一个真正的红色造反者，必须既是革命中的先锋，又","box":[[150,758],[1123,759],[1123,781],[150,780]]},{"text":"是生产上的闯将。我们提出，为了适应备耕生产的特点，一般白天搞生产，晚间闹革命。","box":[[153,797],[1112,797],[1112,817],[153,817]]},{"text":"在《动员令》里，我们还提出地方工业、商业、供销、交通运输等部门，要把支援农业放","box":[[153,835],[1122,835],[1122,855],[153,855]]},{"text":"在首位，保证春耕生产所需要的一切生产资料和生活资料的供应和调拨。机关、学校和其","box":[[153,873],[1123,873],[1123,892],[153,892]]},{"text":"他企事业单位，都要组织力量，有计划地深入农村，宣传毛泽东思想，参加生产劳动，积","box":[[153,910],[1123,910],[1123,930],[153,930]]},{"text":"极参加春耕生产。这个动员令通过报纸、广播发下去以后，我问过一些人，情况怎么样，","box":[[153,947],[1112,947],[1112,967],[153,967]]},{"text":"他们说，出现了前所未有的情况：在城里这么乱的情况下，农村的备耕生产却一点也没受","box":[[154,986],[1122,986],[1122,1005],[154,1005]]},{"text":"什么影响。我对他们说，主要原因有两条：一是毛主席有抓革命促生产的号召，《十六","box":[[153,1022],[1098,1022],[1098,1042],[153,1042]]},{"text":"条》有抓革命促生产的规定；二是农民最讲实际，要吃饭，要生存，怕误农时吃不上饭，","box":[[152,1059],[1111,1059],[1111,1082],[152,1082]]},{"text":"饿肚皮。他们笑了，我也笑了。说真的，我真有点对农村不放心，经他们这么一说，我特","box":[[154,1098],[1122,1098],[1122,1118],[154,1118]]},{"text":"别高兴。","box":[[154,1136],[236,1136],[236,1154],[154,1154]]},{"text":"这里我还要特别提一下革委会成立不久之后召开的全省第一次抓革命促生产春耕生产","box":[[203,1171],[1121,1171],[1121,1191],[203,1191]]},{"text":"工作会议。当时为了不误农时，定在2月1日至6日。这是革委会成立后所召开的第一次县","box":[[154,1211],[1110,1211],[1110,1231],[154,1231]]},{"text":"以上干部会议。在第一天会上，由生产指挥部主任、省军区张万春副司令员主持，我第一","box":[[154,1247],[1121,1247],[1121,1267],[154,1267]]},{"text":"个讲话，潘复生作动员报告。我在会上没有正面讲生产问题，只在会上讲了团结和解放干","box":[[154,1285],[1122,1285],[1122,1305],[154,1305]]},{"text":"部问题。我说，我不具体讲生产，但是，我想大家听了我的这个讲话之后，一定会很好地","box":[[154,1324],[1121,1324],[1121,1341],[154,1341]]},{"text":"把生产搞上去的。因为大家最关心的是干部问题、团结问题。有了干部，有了团结，生产","box":[[153,1360],[1121,1360],[1121,1380],[153,1380]]},{"text":"就会抓上去。","box":[[152,1397],[295,1397],[295,1418],[152,1418]]},{"text":"我没有写讲话稿，大概讲了一个来小时。但是我没有大讲十部政策，而是通篇讲团","box":[[204,1436],[1094,1436],[1094,1453],[204,1453]]},{"text":"结。我说，翻升毛选，从第一篇文章《中国社会各阶级分析》到毛选四卷的最后一篇文章","box":[[152,1473],[1122,1473],[1122,1492],[152,1492]]}],"dimensions":{"height":1650,"width":1275}}