{"ocr_results":[{"text":"除出党后，他们的影响便迅速缩小，越来越不成气候","box":[[76,145],[722,145],[722,168],[76,168]]},{"text":"了。","box":[[76,187],[122,187],[122,211],[76,211]]},{"text":"在反对托陈取消派的右倾宗派活动时，周恩来","box":[[134,229],[723,229],[723,252],[134,252]]},{"text":"仍很注意反对“左”倾错误的斗争。十一月二十二日，","box":[[76,270],[722,270],[722,294],[76,294]]},{"text":"他为中共中央起草致中共驻共产国际代表团的信中","box":[[76,312],[721,313],[721,334],[76,333]]},{"text":"说：“党内右倾的危险却依然存在”，“但这并不是说","box":[[76,352],[723,352],[723,376],[76,376]]},{"text":"“左’倾便不危险了。现在城市工作中尚遇有脱离群","box":[[81,395],[722,395],[722,418],[81,418]]},{"text":"众的盲动情绪，农村工作中尚有不合条件的暴动计","box":[[77,438],[722,438],[722,459],[77,459]]},{"text":"划，甚至还有超乎条件的全省暴动计划，··这都是","box":[[76,478],[722,478],[722,501],[76,501]]},{"text":"值得全党注意，须予以坚决之纠正与肃清的”。①","box":[[74,518],[671,515],[671,543],[75,546]]},{"text":"六大后这一年多时间，对中国共产党来说，正处","box":[[133,562],[722,562],[722,585],[133,585]]},{"text":"在一个严重的历史转折时刻。由于大革命的失败和","box":[[77,604],[721,604],[721,625],[77,625]]},{"text":"“左”倾盲动主义的错误，党和革命遭受了严重的挫","box":[[75,643],[722,645],[722,669],[75,667]]},{"text":"折。一些反动分子断言：共产党已经失败了。可是，","box":[[76,687],[723,687],[723,711],[76,711]]},{"text":"中国共产党人并没有被吓倒，被杀绝。他们在极端艰","box":[[77,730],[721,730],[721,750],[77,750]]},{"text":"难的环境中顽强奋斗，不仅战胜了党内一度存在的","box":[[77,772],[721,772],[721,792],[77,792]]},{"text":"削弱涣散现象，度过了大革命失败后最困难的时期，","box":[[76,812],[722,812],[722,835],[76,835]]},{"text":"重新站稳了脚跟，并且又向前迈进了。这在中国共产","box":[[74,853],[722,852],[722,875],[74,876]]},{"text":"党的历史上，起着承前启后的关键作用。事实证明：","box":[[76,895],[721,896],[721,917],[76,916]]},{"text":"这个时期在周恩来实际主持下的中共中央的路线和","box":[[75,936],[721,937],[721,958],[75,957]]},{"text":"①周恩来：《中共中央致中共驻共产国际代表团的信》，1929年","box":[[121,1016],[723,1013],[724,1037],[121,1039]]},{"text":"11月22日。","box":[[162,1049],[273,1049],[273,1070],[162,1070]]}],"dimensions":{"height":1134,"width":794}}