{"ocr_results":[{"text":"而且还会给日本帝国主义造成进一步灭亡中国的便","box":[[76,145],[722,145],[722,168],[76,168]]},{"text":"利条件，这就使中国的前途更坏。历史的责任，要求","box":[[75,187],[723,187],[723,211],[75,211]]},{"text":"我们争取中国走一个更好的前途。这就要力争说服","box":[[76,229],[723,229],[723,252],[76,252]]},{"text":"蒋介石，只要他答应停止内战、一致抗日的条件，就","box":[[76,270],[723,270],[723,294],[76,294]]},{"text":"释放他回去。蒋介石实际统治着中国的大部分地区，","box":[[74,312],[724,311],[724,334],[74,335]]},{"text":"迫使他走上抗日的道路，还拥护他做全国抗日的领","box":[[76,354],[722,354],[722,375],[76,375]]},{"text":"袖，有利于发动全面的抗日民族解放战争。周恩来提","box":[[77,397],[721,397],[721,417],[77,417]]},{"text":"出这样明确的意见，加强了张学良和平解决西安事","box":[[77,438],[722,438],[722,459],[77,459]]},{"text":"变的决心。","box":[[76,476],[203,478],[202,502],[75,500]]},{"text":"这是一个决定西安事变发展前途的关键性决","box":[[132,519],[723,519],[723,543],[132,543]]},{"text":"策。周恩来当晚给中共中央的电报中，报告了他到西","box":[[75,562],[722,562],[722,585],[75,585]]},{"text":"安后所了解的情况，并说：对蒋介石的处置问题，准","box":[[77,604],[722,604],[722,625],[77,625]]},{"text":"备“答应保蒋安全是可以的，但声明如南京兵挑起内","box":[[76,645],[722,645],[722,668],[76,668]]},{"text":"战，则蒋安全无望”。这个处置办法当即得到中共中","box":[[75,685],[721,686],[721,711],[75,710]]},{"text":"央的认可。第二大，中共中央第一次公开发表宣言，","box":[[77,730],[721,730],[721,750],[77,750]]},{"text":"致电国民党中央，呼吁和平解决西安问题。","box":[[76,771],[610,771],[610,794],[76,794]]},{"text":"由于宋子文即将来西安谈判，周恩来同张学良","box":[[135,812],[722,812],[722,835],[135,835]]},{"text":"在见面当天就一起商定了五项条件：“一、立停内战，","box":[[75,853],[723,853],[723,876],[75,876]]},{"text":"中央军全部开出潼关。二、下令全国援绥抗敌。三、","box":[[76,895],[723,895],[723,918],[76,918]]},{"text":"宋子文负责成立南京过渡政府，肃清一切亲日派。","box":[[75,935],[722,937],[722,960],[75,958]]},{"text":"四、成立抗日联军。五、释放政治犯，实现民主，武","box":[[77,980],[722,980],[722,1000],[77,1000]]},{"text":"①周恩来致中共中央的电报，1936年12月17日。","box":[[121,1047],[608,1048],[608,1071],[121,1070]]}],"dimensions":{"height":1134,"width":794}}