{"ocr_results":[{"text":"天只有一件白长衫，入冬则是单薄的青棉袍，外面再","box":[[75,145],[723,144],[723,168],[75,169]]},{"text":"罩一件已经泛白的蓝大褂。他吃得也很简单。因为没","box":[[77,188],[722,188],[722,212],[77,212]]},{"text":"有钱包饭，几年里都只能在门口零买，或到小饭馆里","box":[[76,230],[722,230],[722,253],[76,253]]},{"text":"零吃，这样可以省些费用。没有菜时，就从家里带一","box":[[75,272],[721,271],[721,295],[75,296]]},{"text":"小罐酱来下饭。《同学录》中也说到：“君家贫，处境","box":[[77,314],[722,314],[722,337],[77,337]]},{"text":"最艰，学费时不济，而独能于万苦千难中多才多艺，","box":[[76,357],[722,357],[722,381],[76,381]]},{"text":"造成斯绩。”①因此，他对社会上的穷苦人充满同情。","box":[[76,399],[722,399],[722,423],[76,423]]},{"text":"他在作文中写道：“踊途中，睹乞与成群也，则思","box":[[77,444],[721,444],[721,465],[77,465]]},{"text":"推己及人，视天下饥如己饥、溺如己溺。”“殊弗欲埋","box":[[76,485],[722,485],[722,508],[76,508]]},{"text":"首窗下，擎孳于字里行间，而置他事于不问也。”少","box":[[75,527],[720,524],[721,552],[75,554]]},{"text":"年时代这种艰苦的境遇和俭朴的生活，对他以后很","box":[[77,571],[721,571],[721,591],[77,591]]},{"text":"有影响。","box":[[75,613],[174,613],[174,637],[75,637]]},{"text":"严修十分器重周恩来的人品和才学，他的儿子","box":[[132,654],[721,655],[721,678],[132,677]]},{"text":"严智崇曾想向周恩来提亲，把妹妹严智安许配给他。","box":[[76,698],[721,698],[721,721],[76,721]]},{"text":"严智安表示年龄尚小，暂时不愿提起婚姻的事情。③","box":[[75,740],[717,738],[717,762],[75,764]]},{"text":"随着年龄的一天天增长，随着对中国国情的加","box":[[133,783],[721,783],[721,806],[133,806]]},{"text":"深了解，周恩来忧国忧民的心情更加炽热了。他在南","box":[[76,825],[721,826],[721,847],[76,846]]},{"text":"开学习那四年间，灾难深重的中华民族的处境正在","box":[[76,868],[722,868],[722,891],[76,891]]},{"text":"①南开学校《第十次毕业同学录》，1917年。","box":[[120,950],[558,949],[558,973],[120,974]]},{"text":"②周恩来作文：《息有居学，载之礼经，人贵惜时，传于宋史，","box":[[120,984],[723,983],[723,1004],[120,1005]]},{"text":"诸生于旧历年假中，欲事何事，益预言之》，手稿。","box":[[160,1017],[638,1017],[638,1037],[160,1037]]},{"text":"③严仁：《周恩来与严修》，《党的文献》，1990年第4期。","box":[[121,1049],[697,1048],[697,1069],[121,1070]]}],"dimensions":{"height":1134,"width":794}}