{"ocr_results":[{"text":"附缘","box":[[140,205],[160,205],[160,274],[140,274]]},{"text":"勃，振人心","box":[[326,204],[353,204],[353,359],[326,359]]},{"text":"不需施肥，无求於人，而不断向人民献繁花。其花小而連片成行，燦若錦绣，生機勃","box":[[366,203],[396,203],[396,1168],[366,1168]]},{"text":"死不了一歌一束","box":[[139,263],[160,263],[160,425],[139,425]]},{"text":"【死不了一是民間普遍種植的一種草本小花，生命力極為頂强，不怕摧折、不怕旱，","box":[[407,262],[434,262],[434,1161],[407,1161]]},{"text":"『死不了赞歌一束","box":[[636,343],[690,343],[690,842],[636,842]]},{"text":"（一九九六年九月二十五日","box":[[526,459],[553,459],[553,736],[526,736]]},{"text":"王平權","box":[[564,553],[600,553],[600,671],[564,671]]},{"text":"—1077—","box":[[174,1204],[273,1204],[273,1223],[174,1223]]}],"dimensions":{"height":1353,"width":957}}