{"ocr_results":[{"text":"第二部上善文遗：文道四十五篇","box":[[162,202],[185,202],[185,459],[162,459]]},{"text":"要有很長時間的門争。","box":[[229,212],[257,211],[259,462],[231,462]]},{"text":"有影響。清除這些影，使各方面、各领域思想上解决問愿，還要作深入細致的工作，還","box":[[270,209],[303,210],[298,1172],[265,1172]]},{"text":"這门争還是在門。各级、各個城都存在這問，他們在内占據導地位，在很多方面都","box":[[311,211],[339,211],[337,1168],[309,1168]]},{"text":"路的門争反映到内，就是兩條路的門争。他说，這一门争現在也没有了结，劉少奇之後","box":[[348,209],[379,209],[378,1170],[347,1170]]},{"text":"革命才始的，一搞社會主義就始了·究竟是搞社會主義，還是搞資本主義？這兩條道","box":[[389,209],[419,209],[417,1171],[387,1171]]},{"text":"了·他没有持過去提的大部不抓。","box":[[470,207],[496,207],[494,611],[467,611]]},{"text":"说大部不抓，是指確有據的間特務都大部不抓·可是後來大到對打倒了的大部都要抓","box":[[506,207],[536,207],[534,1171],[504,1171]]},{"text":"條，文化大革命中我毛主席講過多次。這一點他是持的·但他没有持大部不抓。過去","box":[[547,206],[574,206],[572,1172],[545,1172]]},{"text":"路緣的也好，在内、政府内、民主派内部，即使確有證據的特務，也要一人不殺。這一","box":[[585,207],[612,207],[612,1169],[585,1169]]},{"text":"專政限於很小圍，万内問题，不管走資本主羲道路的當權派也好，固持資產级反動","box":[[625,207],[652,207],[652,1171],[625,1171]]},{"text":"的，持資產级思想的，要没有達法，就不能抓。要事實講道理，同他。他，","box":[[663,204],[694,204],[693,1171],[662,1171]]},{"text":"政機關，保障實現無產级大民主·毛主席反復講，放毒不是指的思想上的問題，思想反動","box":[[704,205],[734,205],[732,1172],[702,1172]]},{"text":"故、暗害、間活動這些現行反革命要事政，依法制裁。革命群衆要發動起來，助督事","box":[[743,207],[773,207],[771,1169],[741,1169]]},{"text":"的殺人放火放毒一放毒不是指说怪話反對導，而是真正去放毒藥。一制造交通事","box":[[781,211],[808,211],[807,1166],[780,1166]]},{"text":"毛主席说，一定要有革命领導幹部参加文化大革命，要打破清规戒律，打破束缚群的","box":[[191,248],[221,248],[218,1171],[188,1171]]},{"text":"毛主席，看起來内兩條路門争還不能说已經解决了。他说，這個門争不是文化大","box":[[429,249],[459,249],[456,1172],[426,1172]]}],"dimensions":{"height":1353,"width":957}}