{"ocr_results":[{"text":"十要達到既促使農產品大增產，又促使直接事田間作业的力人数日益缩减，而田間作","box":[[169,215],[199,214],[203,1176],[173,1176]]},{"text":"的動力用於多種經管·再加上一個要用百分之七十的精力來抓多種經管·這三個百分之七","box":[[211,213],[238,213],[240,1173],[213,1173]]},{"text":"和産後，都要分化成為獨立的工业或商業部門而又聯合起來。","box":[[290,212],[317,212],[320,865],[293,865]]},{"text":"濟作物，難以解决致富問题·種植什磨，又必须因地制宜·","box":[[367,212],[398,211],[402,844],[371,845]]},{"text":"食的收益大體為一比三點五;投資經濟作物的收益大體為一比三點七·一般说，不種植經","box":[[406,210],[437,210],[441,1175],[410,1175]]},{"text":"系已經發生和正在發展的偉大革·","box":[[486,210],[513,210],[515,603],[489,603]]},{"text":"一解决了温鲍問题：第二解决致富問题：第三要進一步解决翻兩番問题，","box":[[566,213],[594,213],[597,993],[569,993]]},{"text":"幹渠、支渠、毛渠交識成網了，土地平整如棋了：淤地後肥力提高了。","box":[[644,210],[671,210],[674,962],[647,962]]},{"text":"利建設？聊城、德州、惠民、荷澤四個地區普遍做了回答：不但不會，而且起了促進作用。","box":[[682,208],[715,208],[719,1170],[686,1170]]},{"text":"的第一將是德州。為什磨大翻身呢？群衆：一靠政策，二靠棉花，三靠黄河水","box":[[761,206],[793,206],[798,1066],[765,1066]]},{"text":"第二部上普文建·文建四十五篇","box":[[147,218],[163,218],[163,465],[147,465]]},{"text":"烟地區新的领導班子，提出了要使百分之七十的收入來自多種經管：要使百分之七十","box":[[250,253],[277,253],[280,1175],[253,1175]]},{"text":"要解决翻兩番，就要解决機、工（副）、商的分立和综合問。即田間作物生產的産前","box":[[329,245],[357,245],[360,1175],[332,1175]]},{"text":"向大业的投資不断增加，開關了大再生產的新局面。民根據經驗計算，投資種植","box":[[446,254],[475,254],[480,1175],[450,1175]]},{"text":"各地重點户、專业户和聯合體已占到總農户的百分之二十五至百分之三十，这是生產開","box":[[525,248],[556,248],[560,1176],[529,1176]]},{"text":"三中全會以來的政策路綫為群案所掌握，就成為改造世界的武器。依靠這個武器，第","box":[[604,248],[634,248],[639,1176],[609,1176]]},{"text":"黄河在山東已經變害河為利河·過去人們曾經心，實行雙包贵任制會不會影響田水","box":[[725,249],[752,249],[756,1173],[729,1173]]},{"text":"2$37","box":[[215,1213],[241,1213],[241,1225],[215,1225]]}],"dimensions":{"height":1353,"width":957}}