{"ocr_results":[{"text":"革小组商量’独断独行’不但背着文革小组’而且背着中央°陈伯达说你们","box":[[199,116],[223,116],[223,754],[199,754]]},{"text":"代表团，陶铸表示不赞成揪王任重。陈伯达说陶铸的态度完全是错误的。他是文革小组顾问，但他对文化大革命的问题，从来不跟文","box":[[250,117],[273,117],[273,1237],[250,1237]]},{"text":"推广是同陶铸有关系的’他想洗刷这一点是洗刷不掉的。后来他又变本加厉地推行刘邓路线。陶铸在北京接见过这一批人（揪王任重","box":[[299,117],[323,117],[323,1238],[299,1238]]},{"text":"宣布。陈伯达在会上说’陶铸到中央后没有执行毛主席为代表的无产阶级革命路线’他实际上是刘邓路线的忠实执行者°刘邓路线的","box":[[348,113],[375,113],[374,1239],[347,1239]]},{"text":"保皇派’保刘少奇、邓小平°打倒陶铸不是突然的’而这个公开宣布是突然的。我至今不知道是为什么°后来知道毛主席不同意这次","box":[[399,115],[426,115],[426,1238],[399,1238]]},{"text":"准备。江青组织的这个会’通知中央文革的人去参加’参加者有陈伯达、康生、江青、我’还有别人°陈伯达宣布陶铸是中国最大的","box":[[450,116],[474,116],[474,1237],[450,1237]]},{"text":"还没醒’就被江青叫去出席会。江青叫陈伯达把陶铸的问题公开宣布。这天接见的对象是湖北省揪王任重的代表团。陈伯达事先没有","box":[[498,115],[525,115],[525,1240],[498,1240]]},{"text":"准公开开大会’更不准在报上公开批判","box":[[675,116],[699,116],[699,449],[675,449]]},{"text":"刘邓都有’陶铸更不成问题。他们的地位变了’但公开批判他们’毛主席还是不准。上面说十二月下旬开了批评陶铸的会’但还是不","box":[[724,113],[751,113],[750,1238],[723,1238]]},{"text":"赞成。毛主席还是把陶铸作为十一中全会选出的常委°十一月二十五日、二十六日毛主席第八次接见红卫兵’还是全体常委都出席，","box":[[776,116],[799,116],[799,1224],[776,1224]]},{"text":"到一九六七年一月四日’突然公开宣布陶铸的问题。陈伯达说这个会是江青组织的。那天陈伯达还没起床’他自己说吃了安眠药","box":[[548,151],[575,151],[574,1239],[547,1239]]},{"text":"（六）公开批判陶铸","box":[[598,163],[625,163],[625,333],[598,333]]}],"dimensions":{"height":1353,"width":957}}