{"ocr_results":[{"text":"第二部未完成的文化大革命回惊绿·第一部分文化大革命的序幕和它的動","box":[[160,203],[180,203],[180,742],[160,742]]},{"text":"東省委不能掌握局面了，省委的指示青島拒绝執行，青島直接找中央，中央支持青島。青島","box":[[201,203],[228,203],[230,1170],[203,1170]]},{"text":"個時間，還是回山東？啟龍表示他不怕群衆，要回山東。啟龍這次回去後就不行了。山","box":[[240,202],[270,202],[271,1170],[241,1170]]},{"text":"來了，我見過他。當時還是文明的，没有武門·當時中央微求啟龍的意見，就在北京待一","box":[[283,204],[310,204],[310,1166],[283,1166]]},{"text":"啟龍成立的红衛兵分化了，啟龍支持保省委的一派。啟龍被造反派的红衛兵帶到北京","box":[[323,204],[350,204],[350,1167],[323,1167]]},{"text":"中表揚的有啟龙、王效禹，说他們站在群方面，摊護毛主席革命路綫。可是很短時間後","box":[[359,202],[390,202],[391,1168],[360,1168]]},{"text":"和江西原來主要負人都没站得住。山東是啟龍。文化大革命剛起來不久，毛主席在批語","box":[[401,202],[429,202],[431,1167],[403,1167]]},{"text":"人说在新疆被盛世才關的一批人都是叛徒（這没有道理，這樣連毛澤民都否定了。）方志纯","box":[[439,202],[469,202],[471,1167],[441,1167]]},{"text":"一開始就乱，方志纯曾在新被盛世才關過·在工作會後，特别是十一十二月，江青等","box":[[477,202],[507,202],[510,1168],[481,1168]]},{"text":"就支持群案揭露葉飛的·後來一直就是韓先楚掌權，韩先楚是四野的。江西是方志纯，江西","box":[[516,201],[546,201],[549,1168],[519,1168]]},{"text":"福建又出現一個情况，軍區司令員韓先楚支持群衆。他于最早的在中央发表支左指示之前","box":[[557,201],[587,201],[590,1168],[560,1168]]},{"text":"無數，很早就發生江華的夫人吴仲廉自殺的事。當時浙江的矛頭對着江華。福建對着葉飛。","box":[[596,200],[626,200],[629,1165],[599,1165]]},{"text":"住杭州。運動開始，毛主席心目中没有要打倒江華，但江華在文革初期對毛主席的意圖心中","box":[[636,200],[666,200],[668,1168],[638,1168]]},{"text":"資産级反動路綫。浙江是江华，同毛主席是老關系，井山就熟。毛主席外出時常","box":[[676,201],[703,201],[705,1167],[678,1167]]},{"text":"批，所以就為江渭清還可以。江渭清最早還掌握着局面，但他也派了工作組，執行了所","box":[[715,200],[746,200],[748,1167],[717,1167]]},{"text":"一書記站不住了江蘇是江渭清，毛主席没有意思要打倒他，因為江渭清過去曾受到劉少奇","box":[[758,207],[785,207],[785,1164],[758,1164]]},{"text":"當時華東的情况：中心是上海，华東毛主席也很重視。華東局乱了以後，华東有些省第","box":[[792,250],[819,250],[821,1161],[795,1161]]},{"text":"一","box":[[203,1208],[212,1208],[212,1216],[203,1216]]},{"text":"563","box":[[230,1203],[263,1203],[263,1220],[230,1220]]}],"dimensions":{"height":1353,"width":957}}