{"ocr_results":[{"text":"第四部·王力毛弹束","box":[[136,200],[157,201],[153,370],[132,369]]},{"text":"的·文中原來没有劉少奇，毛澤東特别加了少奇三個字","box":[[176,198],[205,199],[197,816],[167,815]]},{"text":"無故地说，一以毛澤東和劉少奇為代表的馬克思主義者一這個提法是毛澤东在文字上表達","box":[[215,200],[242,201],[231,1164],[204,1164]]},{"text":"理解毛澤東的哲學思想，而且為，毛東思想同劉少奇的思想是相通的，毛澤東不是白","box":[[253,199],[283,200],[272,1164],[242,1164]]},{"text":"想·到少奇所做的《人為什犯錯》的報告，對我個人來，一子得益很大。我進一步","box":[[292,199],[322,200],[313,1164],[283,1164]]},{"text":"柯施成為政治局成具","box":[[689,201],[716,202],[713,457],[686,457]]},{"text":"不梭可不行。不，你還會重復錯。這不是小問題，這是大問題，這樣我才同意增加","box":[[728,203],[755,204],[746,1168],[719,1168]]},{"text":"他不了解形勢：第二不了解中央内部情况，所以他錯了，劉少奇说，他了，也就行了，","box":[[766,203],[796,204],[784,1161],[755,1160]]},{"text":"劉少奇在山東，不但是在政治路方面宣傅毛東，而且還深刻地宣傳毛澤東的哲學思","box":[[333,245],[360,245],[351,1164],[324,1164]]},{"text":"以毛澤東和劉少奇為代表的中國","box":[[512,348],[555,349],[548,940],[504,940]]},{"text":"馬克思主羲者一是毛澤東提的","box":[[453,388],[493,389],[487,916],[447,916]]},{"text":"869","box":[[187,1199],[222,1199],[222,1217],[187,1217]]}],"dimensions":{"height":1353,"width":957}}