{"ocr_results":[{"text":"第四部·王力蒙毛泽束","box":[[134,207],[158,208],[154,380],[130,379]]},{"text":"際略問题决策這個角度，除了毛東，主要負貴人是少奇·不光國内問题是少奇管，","box":[[175,208],[202,209],[194,1165],[166,1165]]},{"text":"常重要的决策者。是毛東的最重要的辅弼者之一·當然國際共產主義的這個角度，國","box":[[215,208],[242,209],[234,1170],[207,1170]]},{"text":"是一致的，美國的反共專家，利用李志绥的書，辱周恩來，是别有用心的。周恩來也是非","box":[[253,207],[283,208],[275,1170],[245,1170]]},{"text":"的，在這個很長的歷史時期中，中國個主要决策者毛澤東、劉少奇、周恩來、小平，都","box":[[292,206],[322,206],[317,1171],[287,1171]]},{"text":"東看得很清楚·劉少奇也看得很清楚·對于各種矛盾的分析同看法，毛澤東和劉少奇是一致","box":[[332,207],[362,208],[355,1172],[325,1172]]},{"text":"常著的·著的變化，人們容易看清楚。在著變化發生之前，人們常常看不清楚。毛澤","box":[[372,207],[402,208],[396,1173],[366,1173]]},{"text":"界新的變化。兩極對立，冷時期，持了那磨多年·在這個當中，開頭同结束，化是非","box":[[412,207],[440,208],[434,1171],[406,1171]]},{"text":"的，也符合全人類利益的。就是要這樣幹，人類的歷史才能前進。","box":[[490,206],[519,207],[514,914],[484,914]]},{"text":"据·","box":[[572,211],[594,209],[598,252],[576,254]]},{"text":"表現為中國人民同代替日本地位的美國的矛盾·所以中國共產立地作出了自己的略决","box":[[608,207],[638,208],[632,1175],[602,1175]]},{"text":"新獨立國家、民族解放運動之間的矛盾，民族解放運動的潮流，也檔不住·在中國，主要","box":[[647,208],[677,208],[672,1176],[642,1176]]},{"text":"但不是現實的可能性·世界的主要矛盾是帝國主羲、新老殖民主羲同殖民地半殖民地，以及","box":[[687,208],[717,209],[711,1176],[681,1176]]},{"text":"界的主要矛盾不是這個。第三次世界争没有現寶的可能性。不是没有可能，是有可能性，","box":[[727,209],[757,210],[752,1167],[722,1167]]},{"text":"個，害怕爆發第三次世界大，得不敢革命了，以毛東為代表的中國人：這不封。世","box":[[767,210],[796,211],[787,1173],[759,1173]]},{"text":"實際上第二次世界大戳以後最大的事件是中國革命的勝利，而引起一直没有間断的世","box":[[452,250],[479,250],[472,1173],[446,1173]]},{"text":"+","box":[[463,253],[472,253],[472,259],[463,259]]},{"text":"以毛澤東為代表的这樣的决策真正是馬克思主義的决策，也真正是代表我們中國利益","box":[[528,248],[558,248],[553,1175],[523,1175]]},{"text":"891","box":[[198,1207],[227,1207],[227,1223],[198,1223]]}],"dimensions":{"height":1353,"width":957}}