{"ocr_results":[{"text":"（四）關於林彪陰谋政髮毅毛问题","box":[[249,66],[541,67],[541,85],[249,84]]},{"text":"見，毛澤東此時對於倒林一事上的急迫性。","box":[[67,158],[464,161],[464,180],[67,178]]},{"text":"特點二，被毛澤東所召見的黛政軍大員中車除系統的人占了重要","box":[[112,196],[717,198],[717,218],[112,216]]},{"text":"比例、特别是那些掌控北京、上海、武漢、南京、廣州等地的軍除實","box":[[67,234],[718,236],[718,256],[67,254]]},{"text":"權人物，最主要的軍方大員包括許世友、韩先楚、李德生等人。一些","box":[[67,271],[718,273],[718,293],[67,291]]},{"text":"被篇带有林系色彩的軍方人士有劉豐、丁盛、程世清和陳耘等","box":[[68,309],[717,311],[717,331],[68,329]]},{"text":"人，但在毛的一再明確敲打下，劉、丁、程三人已表熊效忠毛，913事","box":[[68,347],[718,349],[718,369],[68,367]]},{"text":"件後丁盛和程世清也没受什座率连。許世友、韩先楚、李德生大軍","box":[[66,384],[718,386],[718,406],[66,404]]},{"text":"區司命，握有軍除實權，他们對政局更具决定性作用，竟他們控制","box":[[67,422],[718,424],[718,444],[67,442]]},{"text":"了京、南京、上海一線，具有足輕重的地位。對毛澤東來，掌","box":[[67,460],[718,462],[718,482],[67,479]]},{"text":"握了這些地方的軍除實權，在與林彪的门争之中毛就立於不败之地","box":[[65,497],[717,499],[717,519],[65,517]]},{"text":"了。","box":[[65,534],[106,534],[106,556],[65,556]]},{"text":"特點三，毛澤東對林彪系統發起的攻整常猛烈·毛探取了预先","box":[[112,572],[717,574],[717,593],[112,591]]},{"text":"定罪、上上線的方法，反復向各地的軍方大員们大满内的路線门","box":[[66,610],[718,611],[718,631],[66,630]]},{"text":"争如何激烈，建50年以来内就出現了10次路镍门争，明白無地","box":[[67,647],[717,649],[717,669],[67,667]]},{"text":"向他们表示1970年8月山九届二中全會上的事没完，是万内的第十","box":[[66,685],[717,687],[717,706],[66,704]]},{"text":"次路線门争，是雨個司令部之間的门争。設國家主席就是反的政治","box":[[67,723],[716,724],[716,742],[67,741]]},{"text":"納领，“天才”是反革命的理。毛澤東在與這些政軍大員","box":[[66,760],[717,761],[717,781],[66,780]]},{"text":"的谈話中其矛頭針對林彪已到了圖匕見無以復加的程度，必欲將林","box":[[65,797],[717,799],[717,818],[65,816]]},{"text":"彪置之死地而後快，其批林的調子甚至遠高於当年打倒劉少奇的程","box":[[67,836],[716,837],[716,855],[67,854]]},{"text":"度。","box":[[64,873],[106,873],[106,895],[64,895]]},{"text":"毛澤東這區區二十天的南巡，在巡各地與黛政軍大員們的","box":[[111,910],[716,911],[716,931],[111,930]]},{"text":"話之中，毛一不講如何發展生產力，促進人民生活的改善，二不如","box":[[65,948],[716,949],[716,969],[65,968]]},{"text":"何l快終止全國因文革造成的混局面，而是一门心思大搞級门","box":[[66,986],[716,987],[716,1007],[66,1006]]},{"text":"争、路線门争，较腦汁要通過非法手段到除自己一手提拔起來的接","box":[[66,1024],[715,1025],[715,1045],[66,1044]]},{"text":"班人·在與華國锋的話中，毛竟然“我看你是满腦子晨業，我是滿","box":[[67,1063],[715,1063],[715,1083],[67,1083]]},{"text":"258","box":[[372,1138],[407,1138],[407,1162],[372,1162]]}],"dimensions":{"height":1173,"width":767}}