{"ocr_results":[{"text":"（七）林彪事件的影","box":[[273,45],[468,46],[468,67],[273,66]]},{"text":"扭曲的歷史：林彪事件的教訓","box":[[168,218],[611,219],[611,248],[168,247]]},{"text":"金秋（著）：丁凯文（）","box":[[273,342],[508,342],[508,363],[273,363]]},{"text":"歷史是什？人們是如何記憶他們自已的過去？政府和社會是怎","box":[[88,495],[693,497],[693,517],[88,515]]},{"text":"樣基於被扭曲的事實來書寫一部可信的歷史，而这些被扭曲事實又恰","box":[[42,533],[693,534],[693,554],[42,553]]},{"text":"恰是不少人所親身經過的呢？","box":[[43,572],[328,572],[328,589],[43,589]]},{"text":"作個人，自己經歷了歷史事件的見證人向一個學者的轉變，","box":[[89,607],[683,609],[683,629],[89,627]]},{"text":"而這段個人經歷在大的歷史環境中甚至带有很強的感情因素·管","box":[[42,644],[693,645],[693,665],[42,664]]},{"text":"一轉變是很困難的，但我相信它是必要的。","box":[[42,683],[463,683],[463,703],[42,703]]},{"text":"我所寫的事件就是1971年9月13日所發生的林彪事件，它改了中","box":[[89,720],[694,722],[694,741],[89,739]]},{"text":"國許多人的命運，其中也包括我自己。事件發生後許多人因此而受苦","box":[[42,756],[694,758],[694,778],[42,776]]},{"text":"受離，許多人甚至至今仍深蒙其離。","box":[[44,796],[377,796],[377,813],[44,813]]},{"text":"事件發生後的雨個星期我的父親消失了，在以後的10年中我們系","box":[[89,833],[694,834],[694,854],[89,853]]},{"text":"毫没有他一點消息，我們甚至不知道他是否仍在人世·我的母親和哥","box":[[43,870],[693,871],[693,891],[43,890]]},{"text":"哥被押多年，然後被押往偏遠的晨村做苦役。我的姐姐和我也被送","box":[[43,907],[694,908],[694,928],[43,927]]},{"text":"往晨場“動改造”，在那裡一待就是很多年。我的妹妹，一個13，","box":[[42,944],[684,946],[684,967],[42,964]]},{"text":"一個才1，也被迫承受這突如其來的“流放”生活以及父母親的消","box":[[43,982],[694,985],[694,1005],[43,1002]]},{"text":"失，只能靠自己的力量來維生。","box":[[43,1020],[336,1020],[336,1040],[43,1040]]},{"text":"640","box":[[352,1119],[389,1119],[389,1142],[352,1142]]}],"dimensions":{"height":1192,"width":756}}