{"ocr_results":[{"text":"重霉林彪罪案","box":[[327,44],[453,44],[453,65],[327,65]]},{"text":"打電話通知劉伯承、徐向前、聂臻、葉劍英今晚9點到人民大會堂参","box":[[59,135],[712,139],[712,160],[59,155]]},{"text":"加中央召開的重要干部大會·随後葉群布置王飛、周宇驰林彪備","box":[[58,172],[711,178],[711,198],[58,192]]},{"text":"當晚的講話稿，内容是公怖杨成武的“罪狀”，有反對毛主席，反對林","box":[[60,210],[709,214],[709,234],[60,230]]},{"text":"彪，反對江青，勾結余立金想搞垮吴法等·布置完，中央辨公來","box":[[58,248],[709,251],[709,272],[58,269]]},{"text":"電話，主席請林彪到人民大會堂的“118\"（毛澤东的時休息室），中","box":[[59,286],[709,290],[709,310],[59,306]]},{"text":"央碰頭會全體成員也都去“碰碰頭”。傍晚，葉群又人民大會堂打電","box":[[59,323],[709,327],[709,347],[59,343]]},{"text":"話回來，毛澤东點了三個題目叫林彪講：反對宗派主羲，反對兩面","box":[[58,361],[709,364],[709,385],[58,382]]},{"text":"派，講“相對”與“對”的證關係，葉叫重新備講話稿。张響生","box":[[58,399],[709,403],[709,423],[58,419]]},{"text":"了當晚林彪在大會上的講話，是“東拉西扯，語無偷次，漏洞百","box":[[52,436],[709,440],[709,460],[52,456]]},{"text":"出，這可能是他臨陣磨檐，更可能是他言不由衷，逢場作。”张雲","box":[[57,474],[709,478],[709,498],[57,495]]},{"text":"生、張堃《“文革”期間，我給林彪當秘書》272一277真）“在人民大會","box":[[55,512],[709,515],[709,535],[55,532]]},{"text":"堂召開的軍除團以上幹部會上，林彪首先講話，宣布杨成武、余立","box":[[57,549],[708,551],[708,571],[57,569]]},{"text":"金、傅崇碧的錯和對他們的處理决定·周恩來在講話中表示護林","box":[[55,587],[709,590],[709,610],[55,607]]},{"text":"彪宣怖的毛澤東的決定和命令，也了杨、余、傅所犯的錯’，肯","box":[[57,624],[708,627],[708,647],[57,644]]},{"text":"定和揚了江青。”（《周恩來年譜（1949一1976）》下卷226真）林彪話","box":[[57,661],[708,664],[708,685],[57,681]]},{"text":"中：“中央在主席那理最近接連开會，開了四次會，主席親自主持","box":[[57,699],[707,702],[707,722],[57,719]]},{"text":"的。會决定撤銷杨成武的代長的職務·要把余立金逮捕起來法","box":[[55,736],[707,739],[707,759],[55,756]]},{"text":"·撤销北京的成司令傅崇碧的職務。”周恩來講話中還了：“我","box":[[55,773],[708,777],[708,798],[55,793]]},{"text":"們要永遠忠於中央文革！你們織續揭發，有可能在杨成武後頭還有","box":[[55,811],[706,814],[706,834],[55,831]]},{"text":"黑後台。”（王年一（大動的年代）291一292真）另據参加了那次大","box":[[55,849],[708,851],[708,871],[55,869]]},{"text":"會、後會在林辦助工作的官偉助回憶：會最後毛澤東出場，在","box":[[56,886],[709,889],[709,910],[56,907]]},{"text":"《東方红）楽警和口號警中走到雨台口手向全髓與會者致意，没","box":[[63,924],[708,927],[708,947],[63,944]]},{"text":"一句話就回去了。這然有向與會人員表示今天會傅達的内容是","box":[[55,962],[707,964],[707,984],[55,982]]},{"text":"毛主席親自做出的“偉大载略决策”的合義。事後林豆豆从外地回到北","box":[[55,999],[707,1003],[707,1023],[55,1020]]},{"text":"京，去問林彪：“杨成武有什問题？為什座打倒他？”林彪竟回答：","box":[[54,1037],[695,1039],[695,1059],[54,1057]]},{"text":"945","box":[[363,1115],[399,1115],[399,1138],[363,1138]]}],"dimensions":{"height":1163,"width":767}}