{"ocr_results":[{"text":"重霉林彪罪案","box":[[316,59],[441,59],[441,76],[316,76]]},{"text":"門。”（（建國以来毛澤東文稿）第十三册230真）","box":[[51,151],[487,151],[487,169],[51,169]]},{"text":"4月29日.周恩来在中央批陳整属集报管全体大會上作結請話，","box":[[97,189],[689,189],[689,206],[97,206]]},{"text":"指出軍委辦事組五位同志在政治上犯了方尚路，組織上犯了宗","box":[[52,227],[702,227],[702,244],[52,244]]},{"text":"派主羲错，但性算遗是人民内部問题，同反共分子陳伯達的問题性","box":[[52,265],[701,265],[701,282],[52,282]]},{"text":"算根本不同·（（周恩来年譜（1949-1976）下卷454真）","box":[[51,302],[554,302],[554,319],[51,319]]},{"text":"△中共中央發出（關於把批陈整風遵勤推向深發展的通知》","box":[[99,340],[695,340],[695,357],[99,357]]},{"text":"决定把陳伯達的“反罪行”携大傅達到的基眉骨幹。","box":[[52,376],[551,376],[551,393],[52,393]]},{"text":"5月1日..首都晚上举行腹祝五一劳勤简焰火晚詹：林彪經周恩來催","box":[[96,414],[702,414],[702,431],[96,431]]},{"text":"促勉强來到天安門城楼後，始終不同毛澤东講話，毛澤東封林彪也视","box":[[52,452],[702,452],[702,469],[52,469]]},{"text":"若不見，冷淡之極，正眼都不看一下，在場的人都感凳到子·林彪价","box":[[52,490],[702,490],[702,507],[52,507]]},{"text":"坐了分罐後便不群而别。（高文（晚年周恩來》322真）","box":[[52,527],[606,527],[606,544],[52,544]]},{"text":"6月9日.據江青秘書楊銀顽回憶，江青在约鱼台17號樓精心布置了","box":[[97,562],[701,562],[701,583],[97,583]]},{"text":"一个照相室·特邀林彪、葉群到约魚台照相·林彪没有思想准，","box":[[51,602],[692,602],[692,619],[51,619]]},{"text":"連子都没有刮·江青盒了給林彪照得好，把他带到10號樱刮子。","box":[[52,638],[696,638],[696,655],[52,655]]},{"text":"林彪：“年大了，有子没有係。”不想刮。葉群忙勤：“江青","box":[[52,676],[701,676],[701,694],[52,694]]},{"text":"同志親自給你照相，不刮子不好，刮了得年輕，精神焕發。”江青","box":[[51,713],[700,713],[700,730],[51,730]]},{"text":"也勤説：“你是的副主席，解放軍的副師，照的相磨有頭袖氣","box":[[52,750],[702,750],[702,767],[52,767]]},{"text":"派。”林彪勉强同意刮了·照相時江青突然提出要林彪把帽子摘掉照","box":[[52,788],[702,788],[702,806],[52,806]]},{"text":"“免冠照”，看樣子林彪很不想摘掉帽子，但是在那種場合又不好什","box":[[51,825],[703,823],[703,843],[51,845]]},{"text":"续，只好把帽子摘掉，扔給他的工作人員：江青又突然提出要林彪摔","box":[[52,863],[703,863],[703,880],[52,880]]},{"text":"著（毛澤東選集）做出看書的檬子，亚命爷工作人真跑回10號樱把她","box":[[51,901],[703,901],[703,918],[51,918]]},{"text":"的（毛澤東選集）四卷合訓本掌去，交給林彪·林彪被溅個大燈烤得","box":[[51,938],[702,938],[702,955],[51,955]]},{"text":"满頭大汗，江青遮給他一條毛巾了擦汗水，弄好姿勢以後，終於","box":[[53,975],[703,975],[703,992],[53,992]]},{"text":"按動了快門·照片後來同時發表在（人民報）和《解放軍畫報》的","box":[[50,1012],[705,1011],[705,1031],[50,1032]]},{"text":"七、八期合刊上。（杨銀禄（江青與林彪》）另據官偉助轉述一“林辦”秘","box":[[51,1050],[705,1049],[705,1069],[51,1070]]},{"text":"989","box":[[360,1126],[394,1126],[394,1146],[360,1146]]}],"dimensions":{"height":1163,"width":767}}