{"ocr_results":[{"text":"第三章非主流思潮及红衛兵思潮比较分析","box":[[106,59],[484,56],[485,80],[106,84]]},{"text":"205","box":[[768,62],[799,62],[799,83],[768,83]]},{"text":"革命新偕段是翁兵武主義的新偕段」、「文化大革命强茹民意·瘋狂","box":[[147,156],[796,156],[796,173],[147,173]]},{"text":"迫害民，是全民大迫害」、「民主主義者在抗暴門争的旗下聯合起","box":[[147,190],[797,190],[797,210],[147,210]]},{"text":"来」、|當權者人人正装，登天安门城楼掀起狂熱的紅衛兵连動，宣揚","box":[[149,227],[796,227],[796,245],[149,245]]},{"text":"第兵赣武，高唱世界革命·控制報刊廣播，操全國舆论·對内專政","box":[[148,263],[796,263],[796,280],[148,280]]},{"text":"暴行·镇壓知識分子：焚書坑儒推行愚民政策·比秦始皇更猫之過！","box":[[146,296],[793,297],[793,317],[145,316]]},{"text":"處人人唯唯諾諾不敢言·陷社會暗無天日，使神州大地百業俱毁，遍","box":[[147,334],[795,334],[795,351],[147,351]]},{"text":"地鐵俄赤身，第山荒鄉，白丁文盲。工人不斡活·晨民不種田：学生","box":[[146,369],[795,369],[795,387],[146,387]]},{"text":"不讀書，教書者牛棚勢役，形形色色流氓高喊革命口號·武门傷民，","box":[[148,405],[792,405],[792,422],[148,422]]},{"text":"残酷迫害：抄家捕人，惨无人道·」1982年1月上海市高级人民法院","box":[[146,439],[796,439],[796,459],[146,459]]},{"text":"经遍覆查：宣告劉文辉无罪，撤銷原判·参见劉文辉：《風雨人生路》","box":[[145,476],[798,476],[798,493],[145,493]]},{"text":"（香港：崇適文化出版展拓有限公司，2005），序言，真1-9、25-29、","box":[[146,511],[789,511],[789,528],[146,528]]},{"text":"52-57、350-351。","box":[[145,548],[307,548],[307,565],[145,565]]},{"text":"6.宋永毅、孫大進：《文化大革命和它的翼端思潮》（香港：田園書屋，","box":[[102,582],[791,580],[791,600],[102,602]]},{"text":"1997），页111。","box":[[143,617],[289,617],[289,637],[143,637]]},{"text":"7.關於遇羅克的情况·参见王晨、張天来：<劃破夜空的星），载周明","box":[[101,652],[795,651],[795,671],[101,672]]},{"text":"主编：《歷史在這裹沉思》，第三册（北京：华夏出版社·1987）：真","box":[[145,688],[792,688],[792,706],[145,706]]},{"text":"253-281。關於遇克的线篇回憶文章：参見徐曉、丁東、徐友漁编：","box":[[145,725],[791,725],[791,742],[145,742]]},{"text":"《遇克遗作與回憶》（北京：中國文聯出版公司，1999）。","box":[[144,759],[669,759],[669,776],[144,776]]},{"text":"8.遇錦：（乾坤特重我頭輕一一回憶我的哥哥遇克>（1981年二稿），","box":[[101,794],[789,793],[789,813],[101,814]]},{"text":"载《遇克遗作與回憶》，真270-371。","box":[[144,831],[490,831],[490,849],[144,849]]},{"text":"9.戚本禹舆其他领等人1967年4月13日接见北京中学红代會代表的講","box":[[103,867],[794,867],[794,884],[103,884]]},{"text":"話，参见北京玻璃總廠紅衔兵聯络站编：《中央首長講話》：真101。有","box":[[142,901],[792,902],[792,920],[142,919]]},{"text":"其他资料記载講話的時間是4月14日：估計是因為接见在13日深夜至","box":[[145,938],[792,938],[792,955],[145,955]]},{"text":"14日凌晨進行。","box":[[143,974],[288,974],[288,991],[143,991]]},{"text":"10.王辰、張天来：《劃破夜幕的陨星），载《歷史在這襄沉思》，第三册，","box":[[105,1010],[786,1010],[786,1027],[105,1027]]},{"text":"页275。","box":[[143,1044],[213,1044],[213,1062],[143,1062]]},{"text":"11.本文引用的遇克日記，均據《遇克遗作舆回憶》，真112-122真","box":[[104,1081],[747,1081],[747,1098],[104,1098]]},{"text":"12.以下引用遇克日記中的文字：用括号注明日記日期。","box":[[104,1116],[643,1116],[643,1133],[104,1133]]},{"text":"13.北京家庭問题研究小组（即遇羅克本人）：（出身论）（1966年7月初稿：","box":[[104,1150],[786,1150],[786,1168],[104,1168]]},{"text":"9月定稿，11月修改），北京：《中学文革報》創刊號：1967年1月18日。","box":[[141,1188],[787,1188],[787,1205],[141,1205]]},{"text":"14.北京家庭問题研究小组：（谈漓满），北京：《中学论壇》創刊號，1967年","box":[[104,1223],[792,1223],[792,1240],[104,1240]]},{"text":"2月27日。","box":[[141,1259],[240,1259],[240,1276],[141,1276]]}],"dimensions":{"height":1385,"width":899}}