{"ocr_results":[{"text":"420","box":[[112,62],[145,62],[145,84],[112,84]]},{"text":"失者的足","box":[[683,58],[799,65],[798,89],[682,82]]},{"text":"的前景。這是徐水良以馬克思主義理剖析社會，取得的重要理","box":[[112,151],[799,155],[799,182],[112,178]]},{"text":"成果。大字報在政策方面基本不脱「左」的框架，因而在關心政策和","box":[[113,191],[797,194],[797,218],[113,215]]},{"text":"現實生活的一般民累中間，以引起強烈共。","box":[[115,232],[593,232],[593,252],[115,252]]},{"text":"四|反潮流和|學理论」","box":[[115,317],[469,319],[468,343],[115,340]]},{"text":"林彪事件後，毛澤束一方面要求恢復國民經濟，作出某些政策","box":[[159,376],[797,378],[797,401],[159,399]]},{"text":"調整，另一方面心反左的方針會衡擎文化大革命的地位。周恩來","box":[[112,412],[797,415],[797,439],[112,436]]},{"text":"主持中央工作，着手進行政策調整，批判極左思潮。很多领導乾部","box":[[113,450],[796,453],[796,476],[113,473]]},{"text":"得到「解放」，重新回到领導尚位，或者改善了處境。經濟政策的調","box":[[111,487],[797,490],[797,514],[111,511]]},{"text":"整使工晨業生產呈現復蘇的象。文化教育也現了轉機。政策調","box":[[111,525],[797,528],[797,551],[111,548]]},{"text":"整的基本方向是烈正左倾政策和「復」一一恢復文革前行之有效的","box":[[112,564],[795,566],[795,586],[112,584]]},{"text":"政策。一系列落實政策的做法顺乎心民意，成不可阻的大勢","box":[[111,599],[796,602],[796,625],[111,622]]},{"text":"所趣。黛内極左文革派這一潮流為修正主義的復辟「回潮」，發起","box":[[112,638],[796,640],[796,661],[112,659]]},{"text":"反撃「回潮」。","box":[[113,675],[246,675],[246,696],[113,696]]},{"text":"1971年底毛澤东阻止批判極左，提出要反對林彪的「極右」實","box":[[158,712],[795,714],[795,737],[157,735]]},{"text":"質，1974年進而發動批林批孔、批判《水浒》反對投降派等運動。","box":[[110,751],[793,752],[793,773],[110,772]]},{"text":"内極左派横極推行毛澤东關於反對極右實質、反對否定文革的指","box":[[111,789],[794,791],[794,810],[111,808]]},{"text":"示，在舆青年思想和切身利益相關的上山下鄉、大學生招生、工","box":[[110,825],[795,827],[795,848],[110,846]]},{"text":"招工、教育等間題上，樹立了一些「反潮流」的青年典型。","box":[[110,862],[689,864],[689,885],[110,883]]},{"text":"與此同時，毛澤東號召學習馬克思主義理，對青年思潮產生","box":[[157,900],[793,901],[793,922],[157,921]]},{"text":"了一定的影響。","box":[[113,939],[267,939],[267,960],[113,960]]},{"text":"1「反潮流」","box":[[107,1031],[260,1031],[260,1055],[107,1055]]},{"text":"「反潮流]語出毛澤東，原來是毛澤東自在獻山會上反對林","box":[[155,1088],[792,1088],[792,1108],[155,1108]]},{"text":"彪為首的一批领導人時所持的「馬列主義原则」，後來内文革派所","box":[[110,1125],[794,1126],[794,1147],[110,1146]]},{"text":"提倡的1反潮流丁是要求反擎向文革前十七年回歸的潮流，目的在放","box":[[110,1164],[792,1164],[792,1184],[110,1184]]},{"text":"持文化大革命的意識形態和「新生事物」。","box":[[110,1200],[545,1201],[545,1221],[110,1220]]},{"text":"林彪事件之後，官方意識形熊在青年中曾經享有過的崇高地位","box":[[157,1236],[793,1237],[793,1259],[157,1258]]},{"text":"TOP杂志网","box":[[297,1280],[588,1280],[588,1324],[297,1324]]},{"text":"LLwww.topzazhi.com.","box":[[299,1327],[602,1329],[602,1352],[299,1350]]}],"dimensions":{"height":1370,"width":899}}