{"ocr_results":[{"text":"第七章四五運動時期的青年思潮","box":[[113,60],[403,57],[403,79],[113,81]]},{"text":"465","box":[[761,58],[791,58],[791,78],[761,78]]},{"text":"即制止武用）、《全縣無產級革命派聯合起來）、（關於毛主席最新","box":[[115,152],[788,149],[788,169],[115,173]]},{"text":"指示的哲學思想>等文章。他的文采很受軍代表識，也得到当地","box":[[114,190],[789,186],[789,206],[114,210]]},{"text":"革委會中一些人的同情和助。大概是由於這個原因，他在1969年","box":[[114,227],[789,223],[789,243],[114,247]]},{"text":"由當地贫下中農和领導推，参加了曲靖師高中教師（文科）培訓","box":[[114,263],[789,260],[789,280],[114,284]]},{"text":"班，奇般地實現了讀書的宿·1971年業後，他到磺山職工子","box":[[113,301],[789,298],[789,318],[113,321]]},{"text":"弟學校任教，後轉到工廠做工會宣傅工作。","box":[[114,338],[540,335],[540,355],[114,358]]},{"text":"1972年他開始釀，1974年寫成（特權>初稿，自己對社","box":[[161,374],[789,371],[789,391],[161,395]]},{"text":"會主義社會基本矛盾和民主制度的看法·此後他數次投書中央领導","box":[[115,412],[789,408],[789,428],[115,432]]},{"text":"人，期望自己的點得到可，业修改文。","box":[[114,449],[563,446],[563,466],[114,469]]},{"text":"1974年冬，他以「馬東伍」的化名，将（特權>部分内容寄給素","box":[[160,485],[789,481],[789,501],[161,506]]},{"text":"不相識的靜宜，請她轉呈毛澤束，没有結果。「馬束伍」的筆名，","box":[[115,523],[785,519],[785,539],[115,543]]},{"text":"意為馬克思一恩格斯一列寧一毛澤東革命隧伍中的普通一兵。","box":[[114,560],[740,556],[741,576],[114,580]]},{"text":"1975年小平主持中央工作時，陳爾音人將（特權）轉交","box":[[160,596],[790,592],[790,612],[161,617]]},{"text":"小平，希望小平閣後，視機會轉呈毛澤東，未果。1976年初，（特","box":[[116,634],[790,630],[790,650],[116,654]]},{"text":"權>全文修改定型。為使毛澤東能接受，陳爾普將標题（特權）","box":[[115,670],[791,667],[791,687],[115,690]]},{"text":"改為（無產級民主革命），亚做删節，於5月寄给毛澤东，仍然","box":[[114,707],[789,704],[789,724],[114,727]]},{"text":"没有回音。","box":[[116,745],[224,745],[224,765],[116,765]]},{"text":"1976年10月，四人被抓。陳爾音為毛澤東晚年所講官僚主","box":[[161,781],[790,777],[790,797],[162,801]]},{"text":"羲者臂級、資產級就在内等觀點，對廣大生活在重不平等制","box":[[116,818],[790,814],[790,834],[116,838]]},{"text":"度下的人民來，有相當的同感和感召力，而華國锋發動宫廷政","box":[[115,856],[791,851],[791,872],[115,876]]},{"text":"變，背民意。於是他用紅油墨全文印出（無產級民主革命），","box":[[114,893],[786,889],[786,908],[114,912]]},{"text":"打算發動新疆的赛福鼎，以<無產級民主革命）為政治，攀","box":[[115,930],[791,926],[791,946],[115,950]]},{"text":"行「武装起義」反對華國锋，成就一番偉業。","box":[[115,967],[549,965],[549,985],[115,987]]},{"text":"1977年秋，陳爾普到廣西南寧，向廣西大學一位業於北京大","box":[[162,1004],[790,1001],[790,1021],[162,1024]]},{"text":"學的教師微询意見，最終放了那個一厢情的、發動赛福鼎「武装","box":[[116,1041],[792,1037],[792,1057],[116,1061]]},{"text":"起義」的荒唐幻想，轉而期望爭取小平等领導人的識。廣西回","box":[[116,1078],[791,1074],[791,1095],[116,1098]]},{"text":"雲南後，他按此設想改寫（無產級民主革命）。複寫後，分别征","box":[[116,1115],[791,1111],[791,1131],[116,1135]]},{"text":"湖南湘潭與四川成都，以「殉道者」之筆名，向《人民日報》、《解放","box":[[116,1152],[791,1148],[791,1168],[116,1172]]},{"text":"軍報》和《紅旗》雜、中國社會科學院和胡喬木，以及廣州中山大","box":[[116,1190],[791,1185],[791,1206],[116,1210]]},{"text":"學學報寄出。","box":[[117,1227],[247,1227],[247,1247],[117,1247]]}],"dimensions":{"height":1356,"width":899}}