{"ocr_results":[{"text":"524","box":[[116,50],[147,50],[147,70],[116,70]]},{"text":"失者的足","box":[[679,52],[795,58],[794,78],[678,72]]},{"text":"的觀點：資本主義工商業改造以後，「随着舊級的消，新的隋級","box":[[117,138],[793,148],[792,172],[116,162]]},{"text":"又起來了」，產生了「新的隋級矛盾」；應當「反對特權隋級的存在」，","box":[[116,177],[789,184],[788,207],[115,200]]},{"text":"「反對新的變相的臂級壓迫」；「管理機構官僚化领導像『級』」；「主","box":[[113,214],[793,221],[792,244],[112,237]]},{"text":"要要廣大社會主義民主，健全社會主義法制來根除三害（官僚主","box":[[117,252],[791,259],[791,280],[116,274]]},{"text":"羲、主觀主羲和宗派主羲一一引者注）」、「建立起足以保障人民自","box":[[117,289],[790,296],[789,317],[116,310]]},{"text":"由民主的法制J等。”文革後續段的社會和制度批判的思潮重提","box":[[115,323],[792,331],[791,356],[114,347]]},{"text":"類似的觀點。值得指出的是，文革中提出社會和制度批判的青年，","box":[[115,363],[786,370],[786,390],[114,384]]},{"text":"大多數没有接觸過1957年的「右派」言，他們也不知道自己的言","box":[[115,400],[790,406],[790,427],[114,421]]},{"text":"竞像是重彈「右派」的老調。他們主觀上是毛澤東和馬克思的述","box":[[115,437],[789,443],[789,465],[114,458]]},{"text":"中寻找識現實的武器。問題的深刻之處在於，七十年代舆1957年","box":[[116,474],[789,481],[789,501],[115,495]]},{"text":"的制度没有根本的變化，這些青年的思想武器和觀察角度也没有根","box":[[115,511],[789,517],[789,538],[114,532]]},{"text":"本的變化，「郁調重彈」來源於社會形熊和社會現象的依然如故。","box":[[113,548],[789,554],[789,575],[113,568]]},{"text":"且，只要社會存在不發生根本性的變化，類似的批判性思潮還會一","box":[[113,585],[788,591],[788,612],[112,606]]},{"text":"再出現，不過，隨着時代的發展，批判的思想理武器可能會有所","box":[[112,623],[788,629],[788,649],[112,643]]},{"text":"變更，例如轉而運用西方的主流政治理。","box":[[113,659],[539,663],[539,684],[112,679]]},{"text":"國際共產主羲運動和社會主義思想史的角度觀察，中國青年","box":[[158,697],[787,703],[786,723],[157,717]]},{"text":"社會批判派對社會主義國家特權制度的分析、「岔路口社會主羲」和","box":[[111,733],[786,740],[785,760],[110,753]]},{"text":"「韩部隋級」的，與蘇聯托洛茨基派和南斯拉夫吉拉斯（德熱拉","box":[[108,770],[786,776],[786,797],[108,791]]},{"text":"斯）的有關點可以是如出一辙。托洛茨基在三十年代分析蘇","box":[[110,808],[785,813],[785,833],[110,828]]},{"text":"制度时有過這樣的述：「蘇聯是一個介乎資本主義和社會主羲之","box":[[110,845],[785,851],[784,871],[110,865]]},{"text":"間的矛盾社會」，在這個社會裹，「生產力還遠遠不足以使國有财產","box":[[110,882],[784,888],[784,908],[110,903]]},{"text":"具有社會主義性質」；社會「保持着資產级性質的分配標，建立","box":[[110,919],[784,925],[783,945],[110,939]]},{"text":"在一種新的社會分化的基上」；「經濟的增長一方面使動者的景","box":[[109,957],[785,962],[785,982],[109,977]]},{"text":"况改善得很慢，另一方面促進了特權層的迅速形成」；「官僚利","box":[[109,993],[784,1000],[783,1020],[109,1014]]},{"text":"用社會的對抗把自己改變成一個與社會主義背道而的不受督的","box":[[109,1031],[783,1037],[782,1057],[109,1051]]},{"text":"層」；「日益增長的矛盾的進一步發展，可以走向社會主羲，也可","box":[[108,1068],[783,1073],[783,1094],[108,1088]]},{"text":"以退回到資本主義」；「在走向社會主義的道路上，工人嘴級將不得","box":[[108,1106],[782,1111],[782,1131],[108,1126]]},{"text":"不推翻官僚。」托洛茨基然不為蘇聯的官僚是一個臂級，但是","box":[[108,1142],[783,1148],[782,1168],[108,1162]]},{"text":"指出：「官僚還不优仅是官僚，而是維埃社會中不折不扣的唯一享","box":[[107,1179],[782,1184],[782,1205],[107,1199]]},{"text":"有特權和發號施令的隋層。」”在這裹，似乎可以看到三十至四十年","box":[[106,1214],[781,1220],[780,1243],[106,1237]]},{"text":"TOP杂志网","box":[[295,1264],[591,1268],[591,1313],[295,1308]]},{"text":"LLwww.topzazhi.com.!","box":[[298,1314],[602,1316],[602,1339],[298,1337]]}],"dimensions":{"height":1357,"width":899}}